reddit_get/__init__.py
reddit_get/cli.py
reddit_get/types/__init__.py
reddit_get/types/enums.py
reddit_get/utils.py
reddit_get-1.1.0.dist-info/METADATA
reddit_get-1.1.0.dist-info/WHEEL
reddit_get-1.1.0.dist-info/entry_points.txt
reddit_get-1.1.0.dist-info/RECORD
