Metadata-Version: 2.1
Name: reddit-get
Version: 1.1.0
Summary: A CLI to get reddit content
Home-page: https://github.com/mikelane/reddit-get
License: MIT
Keywords: reddit,cli
Author: Michael Lane
Author-email: mikelane@gmail.com
Requires-Python: >=3.8.0,<4.0.0
Classifier: Environment :: Console
Classifier: License :: OSI Approved :: MIT License
Classifier: Programming Language :: Python :: 3
Classifier: Programming Language :: Python :: 3.8
Classifier: Programming Language :: Python :: 3.9
Classifier: Programming Language :: Python :: 3.10
Classifier: Programming Language :: Python :: 3.11
Requires-Dist: fire (>=0.5.0,<0.6.0)
Requires-Dist: praw (>=7.7.0,<8.0.0)
Requires-Dist: titlecase (>=2.4,<3.0)
Requires-Dist: toml (>=0.10.2,<0.11.0)
Requires-Dist: typing-extensions (>=4.5.0,<5.0.0)
Project-URL: Repository, https://github.com/mikelane/reddit-get
